celer.py
bin/diagnose
bin/setup
celer_installer-1.3.5.dist-info/LICENSE
celer_installer-1.3.5.dist-info/METADATA
celer_installer-1.3.5.dist-info/WHEEL
celer_installer-1.3.5.dist-info/entry_points.txt
celer_installer-1.3.5.dist-info/top_level.txt
celer_installer-1.3.5.dist-info/RECORD
