Metadata-Version: 2.1
Name: celer-installer
Version: 1.3.5
Summary: This command line tool eases the install of the python version of celer server 
Author-email: Celer <service.celer@gmail.com>
License: MIT License
Project-URL: Homepage, https://github.com/celer-redis/celer-installer
Keywords: celer,server,api,python,celer-server,fast,redis,dbengine,stable,1.0.5
Classifier: License :: OSI Approved :: MIT License
Classifier: Programming Language :: Python
Classifier: Programming Language :: Python :: 3
Requires-Python: >=3.9
License-File: LICENSE
Requires-Dist: colorama >=0.4.6
Provides-Extra: dev
Requires-Dist: pytest ; extra == 'dev'
